htmd/__init__.py
htmd/__main__.py
htmd/password_protect.py
htmd/site.py
htmd/utils.py
htmd/cli/__init__.py
htmd/cli/build.py
htmd/cli/preview.py
htmd/cli/start.py
htmd/cli/templates.py
htmd/cli/verify.py
htmd/example_site/config.toml
htmd/example_site/pages/about.html
htmd/example_site/posts/example.md
htmd/example_site/static/_reset.css
htmd/example_site/static/favicon.svg
htmd/example_site/static/password-protect.js
htmd/example_site/static/style.css
htmd/example_site/templates/404.html
htmd/example_site/templates/_layout.html
htmd/example_site/templates/_list.html
htmd/example_site/templates/all_posts.html
htmd/example_site/templates/all_tags.html
htmd/example_site/templates/author.html
htmd/example_site/templates/day.html
htmd/example_site/templates/index.html
htmd/example_site/templates/month.html
htmd/example_site/templates/post.html
htmd/example_site/templates/tag.html
htmd/example_site/templates/year.html
htmd-6.1.0.dist-info/licenses/LICENSE.txt
htmd-6.1.0.dist-info/METADATA
htmd-6.1.0.dist-info/WHEEL
htmd-6.1.0.dist-info/entry_points.txt
htmd-6.1.0.dist-info/top_level.txt
htmd-6.1.0.dist-info/RECORD
