Metadata-Version: 2.4
Name: htmd
Version: 6.1.0
Summary: Write Markdown and Jinja2 templates to create a website
Author-email: Cody Scott <cody.j.b.scott@gmail.com>
Maintainer-email: Cody Scott <cody.j.b.scott@gmail.com>
Project-URL: Changelog, https://github.com/siecje/htmd/blob/main/CHANGELOG.md
Project-URL: Documentation, https://github.com/siecje/htmd
Project-URL: Homepage, https://github.com/siecje/htmd
Project-URL: Issues, https://github.com/siecje/htmd/issues
Project-URL: Repository, https://github.com/siecje/htmd.git
Classifier: License :: OSI Approved :: MIT License
Classifier: Operating System :: OS Independent
Classifier: Programming Language :: Python :: 3
Requires-Python: >=3.13
License-File: LICENSE.txt
Requires-Dist: beautifulsoup4
Requires-Dist: click
Requires-Dist: cryptography
Requires-Dist: csscompressor
Requires-Dist: feedwerk
Requires-Dist: Flask
Requires-Dist: Flask-FlatPages
Requires-Dist: Frozen-Flask
Requires-Dist: htmlmin2
Requires-Dist: jsmin
Requires-Dist: Pygments
Requires-Dist: watchdog
Provides-Extra: dev
Requires-Dist: coverage; extra == "dev"
Requires-Dist: mypy; extra == "dev"
Requires-Dist: pytest; extra == "dev"
Requires-Dist: PyYAML; extra == "dev"
Requires-Dist: requests; extra == "dev"
Requires-Dist: ruff; extra == "dev"
Requires-Dist: types-Pygments; extra == "dev"
Requires-Dist: types-PyYAML; extra == "dev"
Requires-Dist: types-beautifulsoup4; extra == "dev"
Requires-Dist: types-requests; extra == "dev"
Dynamic: license-file
